secondstate/__init__.py
secondstate/converters.py
secondstate-2.0.0.dist-info/LICENSE
secondstate-2.0.0.dist-info/WHEEL
secondstate-2.0.0.dist-info/METADATA
secondstate-2.0.0.dist-info/RECORD
