Metadata-Version: 2.1
Name: secondstate
Version: 2.0.0
Summary: Utility for generating datetimes within given constraints
Home-page: https://github.com/fruiti-ltd/secondstate
License: BSD-3-Clause
Author: Lewis
Author-email: lewis@fruiti.app
Requires-Python: >=3.8,<4.0
Classifier: License :: OSI Approved :: BSD License
Classifier: Programming Language :: Python :: 3
Classifier: Programming Language :: Python :: 3.8
Classifier: Programming Language :: Python :: 3.9
Project-URL: Repository, https://github.com/fruiti-ltd/secondstate
